demos/__init__.py
songt/__init__.py
songt/cryptool.py
songt/datetime.py
cracker_tools-0.1.4.dist-info/LICENSE
cracker_tools-0.1.4.dist-info/METADATA
cracker_tools-0.1.4.dist-info/WHEEL
cracker_tools-0.1.4.dist-info/top_level.txt
cracker_tools-0.1.4.dist-info/RECORD
