Metadata-Version: 2.1
Name: cracker-tools
Version: 0.1.4
Summary: 逆向工具包
Home-page: UNKNOWN
Author: songtao
Author-email: 
License: UNKNOWN
Platform: UNKNOWN
Classifier: Programming Language :: Python :: 3
Classifier: License :: OSI Approved :: MIT License
Classifier: Operating System :: OS Independent
Requires-Python: >=3
License-File: LICENSE
